depthai_sdk/__init__.py
depthai_sdk/args_parser.py
depthai_sdk/constants.py
depthai_sdk/evaluate.py
depthai_sdk/fps.py
depthai_sdk/logger.py
depthai_sdk/multi_cam.py
depthai_sdk/oak_camera.py
depthai_sdk/previews.py
depthai_sdk/record.py
depthai_sdk/replay.py
depthai_sdk/types.py
depthai_sdk/utils.py
depthai_sdk/classes/__init__.py
depthai_sdk/classes/box_estimator.py
depthai_sdk/classes/enum.py
depthai_sdk/classes/nn_config.py
depthai_sdk/classes/nn_results.py
depthai_sdk/classes/packet_handlers.py
depthai_sdk/classes/packets.py
depthai_sdk/classes/yolo_config.py
depthai_sdk/components/__init__.py
depthai_sdk/components/camera_component.py
depthai_sdk/components/camera_control.py
depthai_sdk/components/camera_helper.py
depthai_sdk/components/component.py
depthai_sdk/components/control_camera_with_nn.py
depthai_sdk/components/imu_component.py
depthai_sdk/components/multi_stage_nn.py
depthai_sdk/components/nn_component.py
depthai_sdk/components/nn_helper.py
depthai_sdk/components/parser.py
depthai_sdk/components/pointcloud_component.py
depthai_sdk/components/pointcloud_helper.py
depthai_sdk/components/stereo_component.py
depthai_sdk/components/stereo_control.py
depthai_sdk/components/template_control_cam_with_nn.py
depthai_sdk/components/template_multi_stage_script.py
depthai_sdk/components/tof_component.py
depthai_sdk/components/tof_control.py
depthai_sdk/components/undistort.py
depthai_sdk/integrations/__init__.py
depthai_sdk/integrations/roboflow.py
depthai_sdk/integrations/ros/__init__.py
depthai_sdk/integrations/ros/depthai2ros.py
depthai_sdk/integrations/ros/depthai2ros2.py
depthai_sdk/integrations/ros/imu_interpolation.py
depthai_sdk/integrations/ros/ros2_streaming.py
depthai_sdk/integrations/ros/ros_base.py
depthai_sdk/managers/__init__.py
depthai_sdk/managers/arg_manager.py
depthai_sdk/managers/blob_manager.py
depthai_sdk/managers/encoding_manager.py
depthai_sdk/managers/nnet_manager.py
depthai_sdk/managers/pipeline_manager.py
depthai_sdk-1.15.1.dist-info/METADATA
depthai_sdk-1.15.1.dist-info/WHEEL
depthai_sdk-1.15.1.dist-info/entry_points.txt
depthai_sdk-1.15.1.dist-info/top_level.txt
depthai_sdk-1.15.1.dist-info/RECORD
